rediscluster/__init__.py
rediscluster/client.py
rediscluster/connection.py
rediscluster/crc.py
rediscluster/exceptions.py
rediscluster/nodemanager.py
rediscluster/pipeline.py
rediscluster/pubsub.py
rediscluster/utils.py
redis_py_cluster_patched-2.1.0.999.25.dist-info/LICENSE
redis_py_cluster_patched-2.1.0.999.25.dist-info/METADATA
redis_py_cluster_patched-2.1.0.999.25.dist-info/WHEEL
redis_py_cluster_patched-2.1.0.999.25.dist-info/top_level.txt
redis_py_cluster_patched-2.1.0.999.25.dist-info/RECORD
