Metadata-Version: 2.1
Name: redis-py-cluster-patched
Version: 2.1.0.999.25
Summary: Library for communicating with Redis Clusters. Built on top of redis-py lib
Home-page: http://github.com/grokzen/redis-py-cluster
Author: Johan Andersson
Author-email: Grokzen@gmail.com
Maintainer: Johan Andersson
Maintainer-email: Grokzen@gmail.com
License: MIT
Download-URL: https://github.com/duke-cliff/redis-py-cluster/archive/2.1.0.999.25.tar.gz
Keywords: redis,redis cluster
Platform: UNKNOWN
Classifier: Development Status :: 5 - Production/Stable
Classifier: Programming Language :: Python
Classifier: Programming Language :: Python :: 2
Classifier: Programming Language :: Python :: 2.7
Classifier: Programming Language :: Python :: 3
Classifier: Programming Language :: Python :: 3.5
Classifier: Programming Language :: Python :: 3.6
Classifier: Programming Language :: Python :: 3.7
Classifier: Programming Language :: Python :: 3.8
Classifier: Environment :: Web Environment
Classifier: Operating System :: POSIX
Classifier: License :: OSI Approved :: MIT License
Requires-Python: >=2.7, !=3.0.*, !=3.1.*, !=3.2.*, !=3.3.*, !=3.4
Requires-Dist: redis (<4.0.0,>=3.0.0)
Requires-Dist: gevent (>=1.5.0)
Requires-Dist: greenlet (>=0.4.16)
Provides-Extra: hiredis
Requires-Dist: hiredis (>=0.1.3) ; extra == 'hiredis'
